humanbingo/__init__.py
humanbingo/application.py
humanbingo/cli.py
humanbingo/humanbingo.py
humanbingo/models.py
humanbingo/parsers.py
humanbingo/writers.py
humanbingo-3.0.1.dist-info/DESCRIPTION.rst
humanbingo-3.0.1.dist-info/METADATA
humanbingo-3.0.1.dist-info/RECORD
humanbingo-3.0.1.dist-info/WHEEL
humanbingo-3.0.1.dist-info/entry_points.txt
humanbingo-3.0.1.dist-info/metadata.json
humanbingo-3.0.1.dist-info/top_level.txt
