Metadata-Version: 2.0
Name: humanbingo
Version: 3.0.1
Summary: Create cards for the "Human Bingo" icebreaker game, with customizable properties and templating
Home-page: https://github.com/leingang/humanbingo
Author: Matthew Leingang
Author-email: mleingang@gmail.com
License: MIT license
Keywords: humanbingo
Platform: UNKNOWN
Classifier: Development Status :: 4 - Beta
Classifier: Intended Audience :: Developers
Classifier: License :: OSI Approved :: MIT License
Classifier: Natural Language :: English
Classifier: Programming Language :: Python :: 2
Classifier: Programming Language :: Python :: 2.6
Classifier: Programming Language :: Python :: 2.7
Classifier: Programming Language :: Python :: 3
Classifier: Programming Language :: Python :: 3.3
Classifier: Programming Language :: Python :: 3.4
Classifier: Programming Language :: Python :: 3.5
Requires-Dist: Click (>=6.0)
Requires-Dist: jinja2 (>=2.9.6)
Requires-Dist: pyyaml (>=3.12)
Requires-Dist: ruamel.yaml (>=0.15.23)
Requires-Dist: weasyprint (>=0.39)
